myfootballanalytics/__init__.py
myfootballanalytics/mfa.py
myfootballanalytics/teams_dict.json
myfootballanalytics-0.0.1.dist-info/METADATA
myfootballanalytics-0.0.1.dist-info/WHEEL
myfootballanalytics-0.0.1.dist-info/licenses/LICENSE
myfootballanalytics-0.0.1.dist-info/RECORD
