Metadata-Version: 2.1
Name: myfootballanalytics
Version: 0.0.1
Summary: A football data analysis tool
Project-URL: Homepage, https://github.com/isamathr/myfootballanalytics
Project-URL: Bug Tracker, https://github.com/isamathr/myfootballanalytics/issues
Project-URL: Documentation, https://github.com/isamathr/myfootballanalytics/blob/main/Instructions_manual.pdf
Author-email: Ilias Samathrakis <iliassamathrakis@gmail.com>
License-File: LICENSE
Classifier: License :: OSI Approved :: MIT License
Classifier: Operating System :: OS Independent
Classifier: Programming Language :: Python :: 3.9
Classifier: Topic :: Database
Classifier: Topic :: Scientific/Engineering :: Visualization
Requires-Python: >=3.7
